moneycarlo/__init__.py
moneycarlo/__main__.py
moneycarlo/contracts.py
moneycarlo-0.1.2.dist-info/LICENSE
moneycarlo-0.1.2.dist-info/METADATA
moneycarlo-0.1.2.dist-info/WHEEL
moneycarlo-0.1.2.dist-info/top_level.txt
moneycarlo-0.1.2.dist-info/RECORD
